chunkgpt/__init__.py
chunkgpt/chunkgpt.py
chunkgpt-0.2.0.dist-info/LICENSE
chunkgpt-0.2.0.dist-info/METADATA
chunkgpt-0.2.0.dist-info/WHEEL
chunkgpt-0.2.0.dist-info/top_level.txt
chunkgpt-0.2.0.dist-info/RECORD
