Metadata-Version: 2.1
Name: chunkgpt
Version: 0.2.0
Summary: A lightweight library for summarizing text that surpasses the token limit of specific OpenAI GPT-based models.
Author-email: David Mays <maysidavid@gmail.com>
Project-URL: Homepage, https://github.com/dimays/chunkgpt
Project-URL: Bug Tracker, https://github.com/dimays/chunkgpt/issues
Classifier: Programming Language :: Python :: 3
Classifier: License :: OSI Approved :: MIT License
Classifier: Operating System :: OS Independent
Requires-Python: >=3.8
License-File: LICENSE
Requires-Dist: aiohttp ==3.8.5
Requires-Dist: aiosignal ==1.3.1
Requires-Dist: async-timeout ==4.0.3
Requires-Dist: attrs ==23.1.0
Requires-Dist: certifi ==2023.7.22
Requires-Dist: charset-normalizer ==3.2.0
Requires-Dist: frozenlist ==1.4.0
Requires-Dist: idna ==3.4
Requires-Dist: multidict ==6.0.4
Requires-Dist: openai ==0.27.8
Requires-Dist: regex ==2023.8.8
Requires-Dist: requests ==2.31.0
Requires-Dist: tiktoken ==0.4.0
Requires-Dist: tqdm ==4.66.1
Requires-Dist: urllib3 ==2.0.4
Requires-Dist: yarl ==1.9.2
